{
  "generated_at": "2025-10-15T00:22:20.650013",
  "overview": {
    "total_activities": 381,
    "available_types": [
      "running"
    ],
    "total_distance_km": 4350.19,
    "total_time_seconds": 1728206,
    "total_time_formatted": "480:03:26",
    "date_range": {},
    "avg_distance_per_activity": 11.42,
    "avg_time_per_activity": "1:15:35"
  },
  "type_breakdown": {
    "running": {
      "name": "跑步",
      "icon": "🏃‍♂️",
      "count": 381,
      "total_distance": 4350.19,
      "total_time": 1728206,
      "avg_distance": 11.42,
      "avg_time": 4535.973753280839,
      "percentage": 100.0
    }
  }
}